[
 {
   "Название категории": "БАДы Swiss Nahrin (Свисс Нарин) Швейцария",
   "URL категории": "shveytsarskie-bady-swiss-nahrin-sviss-narin",
   "id родительской категории": 0,
   "ID категории": 218
 },
 {
   "Название категории": "Витамины",
   "URL категории": "vitaminy",
   "id родительской категории": 218,
   "ID категории": 230
 },
 {
   "Название категории": "Жидкие экстракты",
   "URL категории": "jidkie-ekstrakty",
   "id родительской категории": 230,
   "ID категории": 295
 },
 {
   "Название категории": "Витаминные сиропы",
   "URL категории": "vitaminnye-siropy",
   "id родительской категории": 230,
   "ID категории": 296
 },
 {
   "Название категории": "Капсулированные препараты",
   "URL категории": "kapsulirovannye-preparaty",
   "id родительской категории": 230,
   "ID категории": 297
 },
 {
   "Название категории": "Коктейли",
   "URL категории": "kokteyli",
   "id родительской категории": 230,
   "ID категории": 298
 },
 {
   "Название категории": "Таблетированные препараты",
   "URL категории": "tabletirovannye-preparaty",
   "id родительской категории": 230,
   "ID категории": 299
 },
 {
   "Название категории": "Витаминные конфеты Наросан",
   "URL категории": "vitaminnye-konfety-narosan",
   "id родительской категории": 230,
   "ID категории": 300
 },
 {
   "Название категории": "Приправы",
   "URL категории": "pripravy",
   "id родительской категории": 218,
   "ID категории": 231
 },
 {
   "Название категории": "Тонизирующие чаи",
   "URL категории": "toniziruyuschie-chai",
   "id родительской категории": 218,
   "ID категории": 232
 },
 {
   "Название категории": "Укрепление иммунитета",
   "URL категории": "ukreplenie-immuniteta",
   "id родительской категории": 218,
   "ID категории": 233
 },
 {
   "Название категории": "Здоровые сосуды",
   "URL категории": "zdorovye-sosudy",
   "id родительской категории": 218,
   "ID категории": 234
 },
 {
   "Название категории": "Здоровые суставы",
   "URL категории": "zdorovye-sustavy",
   "id родительской категории": 218,
   "ID категории": 235
 },
 {
   "Название категории": "Нормализация пищеварения, Контроль массы тела",
   "URL категории": "normalizatsiya-pischevareniya-kontrol-massy-tela",
   "id родительской категории": 218,
   "ID категории": 236
 },
 {
   "Название категории": "Косметика Swiss Nahrin (Нарин) Швейцария",
   "URL категории": "shveytsarskaya-kosmetika-swiss-nahrin-narin",
   "id родительской категории": 0,
   "ID категории": 219
 },
 {
   "Название категории": "Уход за кожей лица",
   "URL категории": "uhod-za-kojey-litsa",
   "id родительской категории": 219,
   "ID категории": 237
 },
 {
   "Название категории": "Уход за телом",
   "URL категории": "uhod-za-telom",
   "id родительской категории": 219,
   "ID категории": 238
 },
 {
   "Название категории": "Уход за кожей рук и ног",
   "URL категории": "uhod-za-kojey-ruk-i-nog",
   "id родительской категории": 219,
   "ID категории": 239
 },
 {
   "Название категории": "Уход за волосами",
   "URL категории": "uhod-za-volosami",
   "id родительской категории": 219,
   "ID категории": 240
 },
 {
   "Название категории": "Лечебные кремы для тела",
   "URL категории": "lechebnye-kremy-dlya-tela",
   "id родительской категории": 219,
   "ID категории": 241
 },
 {
   "Название категории": "Эфирные масла",
   "URL категории": "efirnye-masla",
   "id родительской категории": 219,
   "ID категории": 242
 },
 {
   "Название категории": "Ароматические эссенции для ванн",
   "URL категории": "aromaticheskie-essentsii-dlya-vann",
   "id родительской категории": 219,
   "ID категории": 243
 },
 {
   "Название категории": "Солнцезащитная линия",
   "URL категории": "solntsezaschitnaya-liniya",
   "id родительской категории": 219,
   "ID категории": 244
 },
 {
   "Название категории": "Средства для принятия ванн и личной гигиены",
   "URL категории": "sredstva-dlya-prinyatiya-vann-i-lichnoy-gigieny",
   "id родительской категории": 219,
   "ID категории": 245
 },
 {
   "Название категории": "Уход за полостью рта",
   "URL категории": "uhod-za-polostyu-rta",
   "id родительской категории": 219,
   "ID категории": 246
 },
 {
   "Название категории": "Линия чайное дерево",
   "URL категории": "liniya-chaynoe-derevo",
   "id родительской категории": 219,
   "ID категории": 247
 },
 {
   "Название категории": "Экология вашего дома",
   "URL категории": "ekologiya-vashego-doma",
   "id родительской категории": 219,
   "ID категории": 248
 },
 {
   "Название категории": "Чистящие средства",
   "URL категории": "chistyaschie-sredstva",
   "id родительской категории": 248,
   "ID категории": 301
 },
 {
   "Название категории": "Спреи",
   "URL категории": "sprei",
   "id родительской категории": 248,
   "ID категории": 302
 },
 {
   "Название категории": "Transvital Швейцария",
   "URL категории": "shveytsarskaya-kosmetika-transvital-transvital",
   "id родительской категории": 0,
   "ID категории": 220
 },
 {
   "Название категории": "Регенерирующие средства Трансвитал для ухода за кожей лица",
   "URL категории": "regeneriruyuschie-sredstva-transvital-dlya-uhoda-za-kojey-litsa",
   "id родительской категории": 220,
   "ID категории": 249
 },
 {
   "Название категории": "Маска Светового Излучения Transvital Regeneration \"\"Young Again\"\"",
   "URL категории": "maska-svetovogo-izlucheniya-transvital-regeneration-young-again",
   "id родительской категории": 220,
   "ID категории": 250
 },
 {
   "Название категории": "Линия  антивозрастных средств Трансвитал \"\"Совершенство\"\"",
   "URL категории": "liniya-antivozrastnyh-sredstv-transvital-sovershenstvo",
   "id родительской категории": 220,
   "ID категории": 251
 },
 {
   "Название категории": "Очищающие средства Трансвитал для ухода за кожей лица",
   "URL категории": "ochischayuschie-sredstva-transvital-dlya-uhoda-za-kojey-litsa",
   "id родительской категории": 220,
   "ID категории": 252
 },
 {
   "Название категории": "Линия средств Трансвитал для чувствительной кожи \"\"Идеальная защита кожи\"\"",
   "URL категории": "liniya-sredstv-transvital-dlya-chuvstvitelnoy-koji-idealnaya-zaschita-koji",
   "id родительской категории": 220,
   "ID категории": 253
 },
 {
   "Название категории": "Ежедневные антивозрастные средства Трансвитал для ухода за кожей лица",
   "URL категории": "ejednevnye-antivozrastnye-sredstva-transvital-dlya-uhoda-za-kojey-litsa",
   "id родительской категории": 220,
   "ID категории": 254
 },
 {
   "Название категории": "Укрепляющие средства Трансвитал для ухода за кожей",
   "URL категории": "ukreplyayuschie-sredstva-transvital-dlya-uhoda-za-kojey",
   "id родительской категории": 220,
   "ID категории": 255
 },
 {
   "Название категории": "Комплексные увлажняющие средства Трансвитал для ухода за кожей лица",
   "URL категории": "kompleksnye-uvlajnyayuschie-sredstva-transvital-dlya-uhoda-za-kojey-litsa",
   "id родительской категории": 220,
   "ID категории": 256
 },
 {
   "Название категории": "Осветляющие средства Трансвитал  для кожи лица",
   "URL категории": "osvetlyayuschie-sredstva-transvital-dlya-koji-litsa",
   "id родительской категории": 220,
   "ID категории": 257
 },
 {
   "Название категории": "Линия средств Трансвитал для ухода за телом \"\"Совершенство\"\"",
   "URL категории": "liniya-sredstv-transvital-dlya-uhoda-za-telom-sovershenstvo",
   "id родительской категории": 220,
   "ID категории": 258
 },
 {
   "Название категории": "Средства Трансвитал для ухода за кожей лица для мужчин",
   "URL категории": "sredstva-transvital-dlya-uhoda-za-kojey-litsa-dlya-mujchin",
   "id родительской категории": 220,
   "ID категории": 259
 },
 {
   "Название категории": "Линия средств Трансвитал после инъекционных процедур",
   "URL категории": "liniya-sredstv-transvital-posle-inektsionnyh-protsedur",
   "id родительской категории": 220,
   "ID категории": 260
 },
 {
   "Название категории": "Sun Chlorella (Сан Хлорелла) Япония",
   "URL категории": "sun-chlorella-san-hlorella-yaponiya",
   "id родительской категории": 0,
   "ID категории": 221
 },
 {
   "Название категории": "Yukinohada Япония",
   "URL категории": "yukinohada-yaponiya",
   "id родительской категории": 0,
   "ID категории": 222
 },
 {
   "Название категории": "Glo Skin Beauty США",
   "URL категории": "glo-skin-beauty-ssha",
   "id родительской категории": 0,
   "ID категории": 223
 },
 {
   "Название категории": "Очищение и тонизирование",
   "URL категории": "ochischenie-i-tonizirovanie",
   "id родительской категории": 223,
   "ID категории": 267
 },
 {
   "Название категории": "Эксфолианты и Маски",
   "URL категории": "eksfolianty-i-maski",
   "id родительской категории": 223,
   "ID категории": 268
 },
 {
   "Название категории": "Увлажнение",
   "URL категории": "uvlajnenie",
   "id родительской категории": 223,
   "ID категории": 269
 },
 {
   "Название категории": "Восстановление",
   "URL категории": "vosstanovlenie",
   "id родительской категории": 223,
   "ID категории": 270
 },
 {
   "Название категории": "Защита",
   "URL категории": "zaschita",
   "id родительской категории": 223,
   "ID категории": 271
 },
 {
   "Название категории": "Phyto-Active",
   "URL категории": "phyto-active",
   "id родительской категории": 223,
   "ID категории": 272
 },
 {
   "Название категории": "Уход за проблемной кожей",
   "URL категории": "uhod-za-problemnoy-kojey",
   "id родительской категории": 223,
   "ID категории": 273
 },
 {
   "Название категории": "Тонеры",
   "URL категории": "tonery",
   "id родительской категории": 223,
   "ID категории": 274
 },
 {
   "Название категории": "Макияж бровей",
   "URL категории": "makiyaj-brovey",
   "id родительской категории": 223,
   "ID категории": 275
 },
 {
   "Название категории": "Карандаши",
   "URL категории": "karandashi",
   "id родительской категории": 275,
   "ID категории": 303
 },
 {
   "Название категории": "Тени",
   "URL категории": "teni",
   "id родительской категории": 275,
   "ID категории": 304
 },
 {
   "Название категории": "Макияж губ",
   "URL категории": "makiyaj-gub",
   "id родительской категории": 223,
   "ID категории": 276
 },
 {
   "Название категории": "Бальзамы",
   "URL категории": "balzamy",
   "id родительской категории": 276,
   "ID категории": 305
 },
 {
   "Название категории": "Карандаши",
   "URL категории": "karandashi",
   "id родительской категории": 276,
   "ID категории": 306
 },
 {
   "Название категории": "Помады",
   "URL категории": "pomady",
   "id родительской категории": 276,
   "ID категории": 307
 },
 {
   "Название категории": "Макияж глаз",
   "URL категории": "makiyaj-glaz",
   "id родительской категории": 223,
   "ID категории": 277
 },
 {
   "Название категории": "Румяна",
   "URL категории": "rumyana",
   "id родительской категории": 223,
   "ID категории": 278
 },
 {
   "Название категории": "BlanX Италия",
   "URL категории": "blanx-italiya",
   "id родительской категории": 0,
   "ID категории": 224
 },
 {
   "Название категории": "BlanX Classic",
   "URL категории": "blanx-classic",
   "id родительской категории": 224,
   "ID категории": 279
 },
 {
   "Название категории": "BlanX White Shock",
   "URL категории": "blanx-white-shock",
   "id родительской категории": 224,
   "ID категории": 280
 },
 {
   "Название категории": "BlanX PRO",
   "URL категории": "blanx-pro",
   "id родительской категории": 224,
   "ID категории": 281
 },
 {
   "Название категории": "BlanX O3X",
   "URL категории": "blanx-o3x",
   "id родительской категории": 224,
   "ID категории": 282
 },
 {
   "Название категории": "Biorepair Италия",
   "URL категории": "biorepair-italiya",
   "id родительской категории": 0,
   "ID категории": 225
 },
 {
   "Название категории": "Аксессуары",
   "URL категории": "aksessuary",
   "id родительской категории": 225,
   "ID категории": 283
 },
 {
   "Название категории": "Ополаскиватели",
   "URL категории": "opolaskivateli",
   "id родительской категории": 225,
   "ID категории": 284
 },
 {
   "Название категории": "Для детей",
   "URL категории": "dlya-detey",
   "id родительской категории": 225,
   "ID категории": 285
 },
 {
   "Название категории": "Зубные пасты",
   "URL категории": "zubnye-pasty",
   "id родительской категории": 225,
   "ID категории": 286
 },
 {
   "Название категории": "Терапевтический уход",
   "URL категории": "terapevticheskiy-uhod",
   "id родительской категории": 225,
   "ID категории": 287
 },
 {
   "Название категории": "L`Angelica",
   "URL категории": "l-angelica",
   "id родительской категории": 0,
   "ID категории": 227
 },
 {
   "Название категории": "Коллекция БОТАНИКС",
   "URL категории": "kollektsiya-botaniks",
   "id родительской категории": 227,
   "ID категории": 288
 },
 {
   "Название категории": "Коллекция ОФФИСИНАЛИС",
   "URL категории": "kollektsiya-offisinalis",
   "id родительской категории": 227,
   "ID категории": 289
 },
 {
   "Название категории": "Средства по уходу за полостью рта",
   "URL категории": "sredstva-po-uhodu-za-polostyu-rta",
   "id родительской категории": 227,
   "ID категории": 290
 },
 {
   "Название категории": "Масло",
   "URL категории": "maslo",
   "id родительской категории": 227,
   "ID категории": 291
 },
 {
   "Название категории": "Устройство для Педикюра Микро-Педи",
   "URL категории": "ustroystvo-dlya-pedikyura-mikro-pedi",
   "id родительской категории": 0,
   "ID категории": 228
 },
 {
   "Название категории": "Товары для детей",
   "URL категории": "tovary-dlya-detey",
   "id родительской категории": 0,
   "ID категории": 229
 },
 {
   "Название категории": "Нарин",
   "URL категории": "narin",
   "id родительской категории": 229,
   "ID категории": 292
 },
 {
   "Название категории": "Жидкие формулы",
   "URL категории": "jidkie-formuly",
   "id родительской категории": 292,
   "ID категории": 308
 },
 {
   "Название категории": "Капсулированные препараты",
   "URL категории": "kapsulirovannye-preparaty",
   "id родительской категории": 292,
   "ID категории": 309
 },
 {
   "Название категории": "Пре- и пробиотики",
   "URL категории": "pre-i-probiotiki",
   "id родительской категории": 292,
   "ID категории": 310
 },
 {
   "Название категории": "Витаминные конфеты \"\"Наросан\"\"",
   "URL категории": "vitaminnye-konfety-narosan",
   "id родительской категории": 292,
   "ID категории": 311
 },
 {
   "Название категории": "Коктейли",
   "URL категории": "kokteyli",
   "id родительской категории": 292,
   "ID категории": 312
 },
 {
   "Название категории": "Детская Зубная Паста БиоРипейр",
   "URL категории": "detskaya-zubnaya-pasta-bioripeyr",
   "id родительской категории": 229,
   "ID категории": 293
 },
 {
   "Название категории": "Ароматерапия",
   "URL категории": "aromaterapiya",
   "id родительской категории": 229,
   "ID категории": 294
 },
 {
   "Название категории": "Правила",
   "URL категории": "pravila",
   "id родительской категории": 294,
   "ID категории": 313
 },
 {
   "Название категории": "Методы",
   "URL категории": "metody",
   "id родительской категории": 294,
   "ID категории": 314
 },
 {
   "Название категории": "Рекомендации",
   "URL категории": "rekomendatsii",
   "id родительской категории": 294,
   "ID категории": 315
 },
 {
   "Название категории": "Эфирные масла",
   "URL категории": "efirnye-masla",
   "id родительской категории": 294,
   "ID категории": 316
 },
 {
   "Название категории": "Акции",
   "URL категории": "aktsii",
   "id родительской категории": 0,
   "ID категории": 317
 },
 {
   "Название категории": "Наборы",
   "URL категории": "nabory",
   "id родительской категории": 317,
   "ID категории": 319
 }
]